dfsync/__init__.py
dfsync/backends/__init__.py
dfsync/backends/kube.py
dfsync/backends/kube_exec.py
dfsync/backends/rsync.py
dfsync/char_ui.py
dfsync/chcli.py
dfsync/check_dns.py
dfsync/cli.py
dfsync/config.py
dfsync/diffui.py
dfsync/distribution.py
dfsync/exp.py
dfsync/filters.py
dfsync/kube_credentials.py
dfsync/lib.py
dfsync/monitor.py
dfsync/test_dfsync.py
dfsync/test_distribution.py
dfsync/test_kube_credentials.py
dfsync/test_lib.py
dfsync/transactions.py
dfsync-0.4.10.dist-info/METADATA
dfsync-0.4.10.dist-info/WHEEL
dfsync-0.4.10.dist-info/entry_points.txt
dfsync-0.4.10.dist-info/RECORD
