Metadata-Version: 2.3
Name: dfsync
Version: 0.4.10
Summary: 
Author: Mihai Balint
Author-email: balint.mihai@gmail.com
Requires-Python: >=3.8,<4.0
Classifier: Programming Language :: Python :: 3
Classifier: Programming Language :: Python :: 3.8
Classifier: Programming Language :: Python :: 3.9
Classifier: Programming Language :: Python :: 3.10
Classifier: Programming Language :: Python :: 3.11
Classifier: Programming Language :: Python :: 3.12
Classifier: Programming Language :: Python :: 3.13
Requires-Dist: black (==24.3.0)
Requires-Dist: click (>=8,<9)
Requires-Dist: click-default-group (>=1.2.2,<2.0.0)
Requires-Dist: gitpython (>=3.1.14,<4.0.0)
Requires-Dist: kubernetes (>=28.1.0,<29.0.0)
Requires-Dist: paramiko[invoke] (>=3.2.0,<4.0.0)
Requires-Dist: tenacity (>=8.0.1,<9.0.0)
Requires-Dist: toml (>=0.10.2,<0.11.0)
Requires-Dist: watchdog (>=2.0.2,<3.0.0)
